TASK_3/RTL/gpio.v
module gpio_ip (
    input  wire        clk,
    input  wire        reset,
    input  wire        valid,
    input  wire [31:0] addr,
    input  wire [31:0] wdata,
    input  wire [3:0]  wmask,
    output reg  [31:0] rdata,
    inout  wire [31:0] gpio_pin
);

    reg [31:0] gpio_data;
    reg [31:0] gpio_dir;
    wire [31:0] gpio_read;

    // Connect the physical pins
    genvar i;
    generate
        for (i = 0; i < 32; i = i + 1) begin : pin_logic
            assign gpio_pin[i] = gpio_dir[i] ? gpio_data[i] : 1'bz;
            // Read the data register if it is an output, otherwise read the pin
            assign gpio_read[i] = gpio_dir[i] ? gpio_data[i] : gpio_pin[i];
        end
    endgenerate

    // Write Logic
    always @(posedge clk) begin
        if (reset) begin
            gpio_data <= 32'h00000000;
            gpio_dir  <= 32'h00000000;
        end else if (valid) begin
            // Check offset 0x00 for DATA
            if (addr[3:0] == 4'h0 && wmask != 4'b0000) begin
                if (wmask[0]) gpio_data[7:0]   <= wdata[7:0];
                if (wmask[1]) gpio_data[15:8]  <= wdata[15:8];
                if (wmask[2]) gpio_data[23:16] <= wdata[23:16];
                if (wmask[3]) gpio_data[31:24] <= wdata[31:24];
            end
            // Check offset 0x04 for DIR
            else if (addr[3:0] == 4'h4 && wmask != 4'b0000) begin
                if (wmask[0]) gpio_dir[7:0]   <= wdata[7:0];
                if (wmask[1]) gpio_dir[15:8]  <= wdata[15:8];
                if (wmask[2]) gpio_dir[23:16] <= wdata[23:16];
                if (wmask[3]) gpio_dir[31:24] <= wdata[31:24];
            end
        end
    end

    // Read Logic (Always keep the data ready based on the address)
    always @(*) begin
        case (addr[3:0])
            4'h0: rdata = gpio_data;
            4'h4: rdata = gpio_dir;
            4'h8: rdata = gpio_read;
            default: rdata = 32'h00000000;
        endcase
    end

endmodule

TASK_3/RTL/gpio_tb.v
`timescale 1ns / 1ps
`include "gpio.v"
module gpio_tb;

    reg clk;
    reg reset;
    reg valid;
    reg [31:0] addr;
    reg [31:0] wdata;
    reg [3:0] wmask;
    wire [31:0] rdata;
    
    wire [31:0] gpio_pin;

    gpio_ip uut (
        .clk(clk),
        .reset(reset),
        .valid(valid),
        .addr(addr),
        .wdata(wdata),
        .wmask(wmask),
        .rdata(rdata),
        .gpio_pin(gpio_pin)
    );

    // Simulate input signals from the outside world on the upper 16 pins
    assign gpio_pin[31:16] = 16'hAAAA; 

    initial clk = 0;
    always #5 clk = ~clk;

    initial begin
        $dumpfile("gpio_tb.vcd");
        $dumpvars(0, gpio_tb);

        reset = 1;
        valid = 0;
        addr  = 0;
        wdata = 0;
        wmask = 0;
        
        #20 reset = 0;

        // 1. Write to DIR Register (Offset 0x04)
        @(posedge clk);
        #1; 
        valid = 1;
        wmask = 4'b1111;
        addr  = 32'h20000004;
        wdata = 32'h0000FFFF;

        // 2. Write to DATA Register (Offset 0x00)
        @(posedge clk);
        #1;
        addr  = 32'h20000000;
        wdata = 32'h12345678;

        // 3. Read from READ Register (Offset 0x08)
        @(posedge clk);
        #1;
        wmask = 4'b0000;
        addr  = 32'h20000008;

        @(posedge clk);
        #1;
        valid = 0;
        
        #10;
        if (rdata == 32'hAAAA5678) begin
            $display("PASS: Readback verified! Value is %h", rdata);
        end else begin
            $display("FAIL: Expected AAAA5678, got %h", rdata);
        end

        #20 $finish;
    end
endmodule

TASK_3/RTL/gpio_tb.vcd
$date
	Thu Jul  9 10:42:39 2026
$end
$version
	Icarus Verilog
$end
$timescale
	1ps
$end
$scope module gpio_tb $end
$var wire 32 ! gpio_pin [31:0] $end
$var wire 32 " rdata [31:0] $end
$var reg 32 # addr [31:0] $end
$var reg 1 $ clk $end
$var reg 1 % reset $end
$var reg 1 & valid $end
$var reg 32 ' wdata [31:0] $end
$var reg 4 ( wmask [3:0] $end
$scope module uut $end
$var wire 32 ) addr [31:0] $end
$var wire 1 $ clk $end
$var wire 32 * gpio_pin [31:0] $end
$var wire 1 % reset $end
$var wire 1 & valid $end
$var wire 32 + wdata [31:0] $end
$var wire 4 , wmask [3:0] $end
$var wire 32 - gpio_read [31:0] $end
$var reg 32 . gpio_data [31:0] $end
$var reg 32 / gpio_dir [31:0] $end
$var reg 32 0 rdata [31:0] $end
$scope begin pin_logic[0] $end
$var parameter 2 1 i $end
$upscope $end
$scope begin pin_logic[1] $end
$var parameter 2 2 i $end
$upscope $end
$scope begin pin_logic[2] $end
$var parameter 3 3 i $end
$upscope $end
$scope begin pin_logic[3] $end
$var parameter 3 4 i $end
$upscope $end
$scope begin pin_logic[4] $end
$var parameter 4 5 i $end
$upscope $end
$scope begin pin_logic[5] $end
$var parameter 4 6 i $end
$upscope $end
$scope begin pin_logic[6] $end
$var parameter 4 7 i $end
$upscope $end
$scope begin pin_logic[7] $end
$var parameter 4 8 i $end
$upscope $end
$scope begin pin_logic[8] $end
$var parameter 5 9 i $end
$upscope $end
$scope begin pin_logic[9] $end
$var parameter 5 : i $end
$upscope $end
$scope begin pin_logic[10] $end
$var parameter 5 ; i $end
$upscope $end
$scope begin pin_logic[11] $end
$var parameter 5 < i $end
$upscope $end
$scope begin pin_logic[12] $end
$var parameter 5 = i $end
$upscope $end
$scope begin pin_logic[13] $end
$var parameter 5 > i $end
$upscope $end
$scope begin pin_logic[14] $end
$var parameter 5 ? i $end
$upscope $end
$scope begin pin_logic[15] $end
$var parameter 5 @ i $end
$upscope $end
$scope begin pin_logic[16] $end
$var parameter 6 A i $end
$upscope $end
$scope begin pin_logic[17] $end
$var parameter 6 B i $end
$upscope $end
$scope begin pin_logic[18] $end
$var parameter 6 C i $end
$upscope $end
$scope begin pin_logic[19] $end
$var parameter 6 D i $end
$upscope $end
$scope begin pin_logic[20] $end
$var parameter 6 E i $end
$upscope $end
$scope begin pin_logic[21] $end
$var parameter 6 F i $end
$upscope $end
$scope begin pin_logic[22] $end
$var parameter 6 G i $end
$upscope $end
$scope begin pin_logic[23] $end
$var parameter 6 H i $end
$upscope $end
$scope begin pin_logic[24] $end
$var parameter 6 I i $end
$upscope $end
$scope begin pin_logic[25] $end
$var parameter 6 J i $end
$upscope $end
$scope begin pin_logic[26] $end
$var parameter 6 K i $end
$upscope $end
$scope begin pin_logic[27] $end
$var parameter 6 L i $end
$upscope $end
$scope begin pin_logic[28] $end
$var parameter 6 M i $end
$upscope $end
$scope begin pin_logic[29] $end
$var parameter 6 N i $end
$upscope $end
$scope begin pin_logic[30] $end
$var parameter 6 O i $end
$upscope $end
$scope begin pin_logic[31] $end
$var parameter 6 P i $end
$upscope $end
$upscope $end
$upscope $end
$enddefinitions $end
$comment Show the parameter values. $end
$dumpall
b11111 P
b11110 O
b11101 N
b11100 M
b11011 L
b11010 K
b11001 J
b11000 I
b10111 H
b10110 G
b10101 F
b10100 E
b10011 D
b10010 C
b10001 B
b10000 A
b1111 @
b1110 ?
b1101 >
b1100 =
b1011 <
b1010 ;
b1001 :
b1000 9
b111 8
b110 7
b101 6
b100 5
b11 4
b10 3
b1 2
b0 1
$end
#0
$dumpvars
bx 0
bx /
bx .
bx -
b0 ,
b0 +
bx *
b0 )
b0 (
b0 '
0&
1%
0$
b0 #
bx "
bx !
$end
#5000
b1010101010101010zzzzzzzzzzzzzzzz -
b1010101010101010zzzzzzzzzzzzzzzz !
b1010101010101010zzzzzzzzzzzzzzzz *
b0 "
b0 0
b0 /
b0 .
1$
#10000
0$
#15000
1$
#20000
0$
0%
#25000
1$
#26000
b1111111111111111 '
b1111111111111111 +
b100000000000000000000000000100 #
b100000000000000000000000000100 )
b1111 (
b1111 ,
1&
#30000
0$
#35000
b10101010101010100000000000000000 !
b10101010101010100000000000000000 *
b10101010101010100000000000000000 -
b1111111111111111 "
b1111111111111111 0
b1111111111111111 /
1$
#36000
b0 "
b0 0
b10010001101000101011001111000 '
b10010001101000101011001111000 +
b100000000000000000000000000000 #
b100000000000000000000000000000 )
#40000
0$
#45000
b10101010101010100101011001111000 !
b10101010101010100101011001111000 *
b10101010101010100101011001111000 -
b10010001101000101011001111000 "
b10010001101000101011001111000 0
b10010001101000101011001111000 .
1$
#46000
b10101010101010100101011001111000 "
b10101010101010100101011001111000 0
b100000000000000000000000001000 #
b100000000000000000000000001000 )
b0 (
b0 ,
#50000
0$
#55000
1$
#56000
0&
