TASK_4/RTL/pwm.v
// =============================================================================
// pwm_ip - Single-Channel PWM IP for VSDSquadron RISC-V SoC
// -----------------------------------------------------------------------------
// Memory-mapped, 32-bit registers, word-aligned.
//
// Base: PWM_BASE (assigned in SOC integration, e.g., 0x30000000)
// -----------------------------------------------------------------------------
//  Offset | Name   | R/W | Description
//  0x00   | CTRL   | R/W | Enable and polarity
//  0x04   | PERIOD | R/W | PWM period in clock ticks (>= 1)
//  0x08   | DUTY   | R/W | High time in clock ticks
//  0x0C   | STATUS | R   | Debug status  (bit0 = RUNNING, [31:16] = current cnt)
// -----------------------------------------------------------------------------
// CTRL bits:
//   bit 0 : EN  (1 = enable PWM output)
//   bit 1 : POL (0 = active-high, 1 = active-low)
// -----------------------------------------------------------------------------
// PWM output rule:
//   Let cnt run 0..PERIOD-1.
//     pwm_raw = (cnt < DUTY)
//     pwm_out = POL ? ~pwm_raw : pwm_raw
//   When EN = 0, pwm_out is forced to the inactive level (POL selects level).
// =============================================================================
module pwm_ip (
    input  wire        clk,
    input  wire        reset,     // synchronous, active-high
    input  wire        valid,     // bus transaction valid (chip-select)
    input  wire [31:0] addr,      // byte address (only addr[3:0] decoded here)
    input  wire [31:0] wdata,
    input  wire [3:0]  wmask,     // per-byte write mask (0 => read)
    output reg  [31:0] rdata,
    output wire        pwm_out    // PWM output to LED / GPIO / pin
);

    // -----------------------------------------------------------------
    // Register storage
    // -----------------------------------------------------------------
    reg [31:0] ctrl_reg;
    reg [31:0] period_reg;
    reg [31:0] duty_reg;
    reg [31:0] counter;

    wire en   = ctrl_reg[0];
    wire pol  = ctrl_reg[1];

    // -----------------------------------------------------------------
    // Register write logic (byte-strobed)
    // -----------------------------------------------------------------
    always @(posedge clk) begin
        if (reset) begin
            ctrl_reg   <= 32'h0;
            period_reg <= 32'd1;       // safe default: period = 1
            duty_reg   <= 32'h0;
        end else if (valid && (wmask != 4'b0000)) begin
            case (addr[3:0])
                4'h0: begin // CTRL
                    if (wmask[0]) ctrl_reg[ 7: 0] <= wdata[ 7: 0];
                    if (wmask[1]) ctrl_reg[15: 8] <= wdata[15: 8];
                    if (wmask[2]) ctrl_reg[23:16] <= wdata[23:16];
                    if (wmask[3]) ctrl_reg[31:24] <= wdata[31:24];
                end
                4'h4: begin // PERIOD
                    if (wmask[0]) period_reg[ 7: 0] <= wdata[ 7: 0];
                    if (wmask[1]) period_reg[15: 8] <= wdata[15: 8];
                    if (wmask[2]) period_reg[23:16] <= wdata[23:16];
                    if (wmask[3]) period_reg[31:24] <= wdata[31:24];
                end
                4'h8: begin // DUTY
                    if (wmask[0]) duty_reg[ 7: 0] <= wdata[ 7: 0];
                    if (wmask[1]) duty_reg[15: 8] <= wdata[15: 8];
                    if (wmask[2]) duty_reg[23:16] <= wdata[23:16];
                    if (wmask[3]) duty_reg[31:24] <= wdata[31:24];
                end
                default: ; // undefined offsets: writes ignored
            endcase
        end
    end

    // -----------------------------------------------------------------
    // Free-running counter (0 .. PERIOD-1) while enabled
    // -----------------------------------------------------------------
    always @(posedge clk) begin
        if (reset) begin
            counter <= 32'h0;
        end else if (!en) begin
            counter <= 32'h0;
        end else if (period_reg == 32'd0) begin
            counter <= 32'h0;
        end else if (counter >= (period_reg - 32'd1)) begin
            counter <= 32'h0;
        end else begin
            counter <= counter + 32'd1;
        end
    end

    // -----------------------------------------------------------------
    // PWM output generation
    //   DUTY = 0            => always low  (inactive)
    //   DUTY >= PERIOD      => always high (fully active)
    //   otherwise           => high while counter < DUTY
    //   EN = 0              => forced to inactive level (POL-selected)
    // -----------------------------------------------------------------
    wire pwm_raw = (counter < duty_reg);
    wire pwm_active_level = pol ? ~pwm_raw : pwm_raw;
    wire pwm_inactive     = pol ? 1'b1     : 1'b0;

    assign pwm_out = en ? pwm_active_level : pwm_inactive;

    // -----------------------------------------------------------------
    // Read logic (combinational)
    // -----------------------------------------------------------------
    always @(*) begin
        case (addr[3:0])
            4'h0: rdata = {30'b0, pol, en};                 // CTRL
            4'h4: rdata = period_reg;                       // PERIOD
            4'h8: rdata = duty_reg;                         // DUTY
            4'hC: rdata = {counter[15:0], 15'b0, en};       // STATUS (debug)
            default: rdata = 32'h0;
        endcase
    end

endmodule

TASK_5/ip/pwm/test/pwm_tb.v
`timescale 1ns / 1ps
`include "pwm.v"

// =============================================================================
// pwm_tb - Testbench for pwm_ip
//   * Programs PERIOD and DUTY through the memory-mapped bus interface
//   * Observes pwm_out waveform
//   * Verifies duty ratio in one full period
//   * Dumps VCD for GTKWave viewing (pwm_tb.vcd)
// =============================================================================
module pwm_tb;

    reg         clk;
    reg         reset;
    reg         valid;
    reg  [31:0] addr;
    reg  [31:0] wdata;
    reg  [3:0]  wmask;
    wire [31:0] rdata;
    wire        pwm_out;

    // Design under test
    pwm_ip uut (
        .clk    (clk),
        .reset  (reset),
        .valid  (valid),
        .addr   (addr),
        .wdata  (wdata),
        .wmask  (wmask),
        .rdata  (rdata),
        .pwm_out(pwm_out)
    );

    // 100 MHz test clock (period = 10 ns)
    initial clk = 0;
    always #5 clk = ~clk;

    // Sample the PWM output every cycle to measure high time
    integer high_count;
    integer sample_count;

    // Bus write helper task
    task bus_write(input [31:0] a, input [31:0] d);
        begin
            @(posedge clk); #1;
            valid = 1;
            wmask = 4'b1111;
            addr  = a;
            wdata = d;
            @(posedge clk); #1;
            valid = 0;
            wmask = 4'b0000;
        end
    endtask

    initial begin
        $dumpfile("pwm_tb.vcd");
        $dumpvars(0, pwm_tb);

        // Init
        reset = 1;
        valid = 0;
        addr  = 0;
        wdata = 0;
        wmask = 0;
        high_count   = 0;
        sample_count = 0;

        #25 reset = 0;

        // Program PERIOD = 10, DUTY = 3 (30% duty), POL = 0, EN = 1
        bus_write(32'h30000004, 32'd10);   // PERIOD
        bus_write(32'h30000008, 32'd3);    // DUTY
        bus_write(32'h30000000, 32'h1);    // CTRL: EN=1, POL=0

        // Let PWM run 5 full periods and measure duty over one period after settle.
        // 5 periods = 50 cycles; sample 10 cycles = one full period.
        repeat (20) @(posedge clk);        // let counter settle

        // Sample the next full period (10 clock cycles)
        repeat (10) begin
            @(posedge clk); #1;
            sample_count = sample_count + 1;
            if (pwm_out) high_count = high_count + 1;
        end

        $display("Sampled %0d cycles, pwm_out was HIGH for %0d cycles (expected 3).",
                 sample_count, high_count);
        if (high_count == 3)
            $display("PASS: Duty ratio verified (3/10 = 30%%).");
        else
            $display("FAIL: Duty ratio incorrect. Got %0d, expected 3.", high_count);

        // Reprogram DUTY to 7 (70%) and briefly observe
        bus_write(32'h30000008, 32'd7);
        high_count   = 0;
        sample_count = 0;
        repeat (20) @(posedge clk);
        repeat (10) begin
            @(posedge clk); #1;
            sample_count = sample_count + 1;
            if (pwm_out) high_count = high_count + 1;
        end
        $display("After DUTY=7: high for %0d/10 cycles (expected 7).", high_count);
        if (high_count == 7)
            $display("PASS: Duty update verified (7/10 = 70%%).");
        else
            $display("FAIL: Duty update incorrect. Got %0d, expected 7.", high_count);

        // Test polarity inversion (POL = 1)
        bus_write(32'h30000000, 32'h3);    // EN=1, POL=1
        high_count   = 0;
        sample_count = 0;
        repeat (20) @(posedge clk);
        repeat (10) begin
            @(posedge clk); #1;
            sample_count = sample_count + 1;
            if (pwm_out) high_count = high_count + 1;
        end
        $display("With POL=1, DUTY=7: high for %0d/10 cycles (expected 3).", high_count);
        if (high_count == 3)
            $display("PASS: Polarity inversion verified.");
        else
            $display("FAIL: Polarity inversion incorrect. Got %0d, expected 3.", high_count);

        // Disable and check output goes to inactive level
        bus_write(32'h30000000, 32'h2);    // EN=0, POL=1 => inactive = 1
        @(posedge clk); #1;
        if (pwm_out === 1'b1)
            $display("PASS: EN=0 with POL=1 forces output high (inactive).");
        else
            $display("FAIL: EN=0 with POL=1 did not force output high, got %b.", pwm_out);

        bus_write(32'h30000000, 32'h0);    // EN=0, POL=0 => inactive = 0
        @(posedge clk); #1;
        if (pwm_out === 1'b0)
            $display("PASS: EN=0 with POL=0 forces output low (inactive).");
        else
            $display("FAIL: EN=0 with POL=0 did not force output low, got %b.", pwm_out);

        #50 $finish;
    end
endmodule

TASK_4/RTL/pwm_tb.vcd
$date
	Thu Jul 23 12:11:57 2026
$end
$version
	Icarus Verilog
$end
$timescale
	1ps
$end
$scope module pwm_tb $end
$var wire 32 ! rdata [31:0] $end
$var wire 1 " pwm_out $end
$var reg 32 # addr [31:0] $end
$var reg 1 $ clk $end
$var reg 1 % reset $end
$var reg 1 & valid $end
$var reg 32 ' wdata [31:0] $end
$var reg 4 ( wmask [3:0] $end
$var integer 32 ) high_count [31:0] $end
$var integer 32 * sample_count [31:0] $end
$scope module uut $end
$var wire 32 + addr [31:0] $end
$var wire 1 $ clk $end
$var wire 1 % reset $end
$var wire 1 & valid $end
$var wire 32 , wdata [31:0] $end
$var wire 4 - wmask [3:0] $end
$var wire 1 . pwm_raw $end
$var wire 1 " pwm_out $end
$var wire 1 / pwm_inactive $end
$var wire 1 0 pwm_active_level $end
$var wire 1 1 pol $end
$var wire 1 2 en $end
$var reg 32 3 counter [31:0] $end
$var reg 32 4 ctrl_reg [31:0] $end
$var reg 32 5 duty_reg [31:0] $end
$var reg 32 6 period_reg [31:0] $end
$var reg 32 7 rdata [31:0] $end
$upscope $end
$scope task bus_write $end
$var reg 32 8 a [31:0] $end
$var reg 32 9 d [31:0] $end
$upscope $end
$upscope $end
$enddefinitions $end
$comment Show the parameter values. $end
$dumpall
$end
#0
$dumpvars
bx 9
bx 8
b0xx 7
bx 6
bx 5
bx 4
bx 3
x2
x1
x0
x/
x.
b0 -
b0 ,
b0 +
b0 *
b0 )
b0 (
b0 '
0&
1%
0$
b0 #
x"
b0xx !
$end
#5000
0"
0/
b0 !
b0 7
00
02
01
0.
b0 5
b1 6
b0 4
b0 3
1$
#10000
0$
#15000
1$
#20000
0$
#25000
1$
b1010 9
b110000000000000000000000000100 8
0%
#26000
b1 !
b1 7
b1010 '
b1010 ,
b110000000000000000000000000100 #
b110000000000000000000000000100 +
b1111 (
b1111 -
1&
#30000
0$
#35000
b1010 !
b1010 7
b1010 6
1$
#36000
b11 9
b110000000000000000000000001000 8
b0 (
b0 -
0&
#40000
0$
#45000
1$
#46000
b0 !
b0 7
b11 '
b11 ,
b110000000000000000000000001000 #
b110000000000000000000000001000 +
b1111 (
b1111 -
1&
#50000
0$
#55000
b11 !
b11 7
10
1.
b11 5
1$
#56000
b1 9
b110000000000000000000000000000 8
b0 (
b0 -
0&
#60000
0$
#65000
1$
#66000
b0 !
b0 7
b1 '
b1 ,
b110000000000000000000000000000 #
b110000000000000000000000000000 +
b1111 (
b1111 -
1&
#70000
0$
#75000
1"
b1 !
b1 7
12
b1 4
1$
#76000
b0 (
b0 -
0&
#80000
0$
#85000
b1 3
1$
#90000
0$
#95000
b10 3
1$
#100000
0$
#105000
0"
00
0.
b11 3
1$
#110000
0$
#115000
b100 3
1$
#120000
0$
#125000
b101 3
1$
#130000
0$
#135000
b110 3
1$
#140000
0$
#145000
b111 3
1$
#150000
0$
#155000
b1000 3
1$
#160000
0$
#165000
b1001 3
1$
#170000
0$
#175000
1"
10
1.
b0 3
1$
#180000
0$
#185000
b1 3
1$
#190000
0$
#195000
b10 3
1$
#200000
0$
#205000
0"
00
0.
b11 3
1$
#210000
0$
#215000
b100 3
1$
#220000
0$
#225000
b101 3
1$
#230000
0$
#235000
b110 3
1$
#240000
0$
#245000
b111 3
1$
#250000
0$
#255000
b1000 3
1$
#260000
0$
#265000
b1001 3
1$
#270000
0$
#275000
1"
10
1.
b0 3
1$
#280000
0$
#285000
b1 3
1$
#286000
b1 )
b1 *
#290000
0$
#295000
b10 3
1$
#296000
b10 )
b10 *
#300000
0$
#305000
0"
00
0.
b11 3
1$
#306000
b11 *
#310000
0$
#315000
b100 3
1$
#316000
b100 *
#320000
0$
#325000
b101 3
1$
#326000
b101 *
#330000
0$
#335000
b110 3
1$
#336000
b110 *
#340000
0$
#345000
b111 3
1$
#346000
b111 *
#350000
0$
#355000
b1000 3
1$
#356000
b1000 *
#360000
0$
#365000
b1001 3
1$
#366000
b1001 *
#370000
0$
#375000
1"
10
1.
b0 3
1$
#376000
b111 9
b110000000000000000000000001000 8
b11 )
b1010 *
#380000
0$
#385000
b1 3
1$
#386000
b11 !
b11 7
b111 '
b111 ,
b110000000000000000000000001000 #
b110000000000000000000000001000 +
b1111 (
b1111 -
1&
#390000
0$
#395000
b111 !
b111 7
b10 3
b111 5
1$
#396000
b0 *
b0 )
b0 (
b0 -
0&
#400000
0$
#405000
b11 3
1$
#410000
0$
#415000
b100 3
1$
#420000
0$
#425000
b101 3
1$
#430000
0$
#435000
b110 3
1$
#440000
0$
#445000
0"
00
0.
b111 3
1$
#450000
0$
#455000
b1000 3
1$
#460000
0$
#465000
b1001 3
1$
#470000
0$
#475000
1"
10
1.
b0 3
1$
#480000
0$
#485000
b1 3
1$
#490000
0$
#495000
b10 3
1$
#500000
0$
#505000
b11 3
1$
#510000
0$
#515000
b100 3
1$
#520000
0$
#525000
b101 3
1$
#530000
0$
#535000
b110 3
1$
#540000
0$
#545000
0"
00
0.
b111 3
1$
#550000
0$
#555000
b1000 3
1$
#560000
0$
#565000
b1001 3
1$
#570000
0$
#575000
1"
10
1.
b0 3
1$
#580000
0$
#585000
b1 3
1$
#590000
0$
#595000
b10 3
1$
#600000
0$
#605000
b11 3
1$
#606000
b1 )
b1 *
#610000
0$
#615000
b100 3
1$
#616000
b10 )
b10 *
#620000
0$
#625000
b101 3
1$
#626000
b11 )
b11 *
#630000
0$
#635000
b110 3
1$
#636000
b100 )
b100 *
#640000
0$
#645000
0"
00
0.
b111 3
1$
#646000
b101 *
#650000
0$
#655000
b1000 3
1$
#656000
b110 *
#660000
0$
#665000
b1001 3
1$
#666000
b111 *
#670000
0$
#675000
1"
10
1.
b0 3
1$
#676000
b101 )
b1000 *
#680000
0$
#685000
b1 3
1$
#686000
b110 )
b1001 *
#690000
0$
#695000
b10 3
1$
#696000
b11 9
b110000000000000000000000000000 8
b111 )
b1010 *
#700000
0$
#705000
b11 3
1$
#706000
b1 !
b1 7
b11 '
b11 ,
b110000000000000000000000000000 #
b110000000000000000000000000000 +
b1111 (
b1111 -
1&
#710000
0$
#715000
0"
00
1/
b11 !
b11 7
11
b100 3
b11 4
1$
#716000
b0 *
b0 )
b0 (
b0 -
0&
#720000
0$
#725000
b101 3
1$
#730000
0$
#735000
b110 3
1$
#740000
0$
#745000
1"
10
0.
b111 3
1$
#750000
0$
#755000
b1000 3
1$
#760000
0$
#765000
b1001 3
1$
#770000
0$
#775000
0"
00
1.
b0 3
1$
#780000
0$
#785000
b1 3
1$
#790000
0$
#795000
b10 3
1$
#800000
0$
#805000
b11 3
1$
#810000
0$
#815000
b100 3
1$
#820000
0$
#825000
b101 3
1$
#830000
0$
#835000
b110 3
1$
#840000
0$
#845000
1"
10
0.
b111 3
1$
#850000
0$
#855000
b1000 3
1$
#860000
0$
#865000
b1001 3
1$
#870000
0$
#875000
0"
00
1.
b0 3
1$
#880000
0$
#885000
b1 3
1$
#890000
0$
#895000
b10 3
1$
#900000
0$
#905000
b11 3
1$
#910000
0$
#915000
b100 3
1$
#920000
0$
#925000
b101 3
1$
#926000
b1 *
#930000
0$
#935000
b110 3
1$
#936000
b10 *
#940000
0$
#945000
1"
10
0.
b111 3
1$
#946000
b1 )
b11 *
#950000
0$
#955000
b1000 3
1$
#956000
b10 )
b100 *
#960000
0$
#965000
b1001 3
1$
#966000
b11 )
b101 *
#970000
0$
#975000
0"
00
1.
b0 3
1$
#976000
b110 *
#980000
0$
#985000
b1 3
1$
#986000
b111 *
#990000
0$
#995000
b10 3
1$
#996000
b1000 *
#1000000
0$
#1005000
b11 3
1$
#1006000
b1001 *
#1010000
0$
#1015000
b100 3
1$
#1016000
b10 9
b1010 *
#1020000
0$
#1025000
b101 3
1$
#1026000
b10 '
b10 ,
b1111 (
b1111 -
1&
#1030000
0$
#1035000
1"
b10 !
b10 7
02
b110 3
b10 4
1$
#1036000
b0 (
b0 -
0&
#1040000
0$
#1045000
b0 3
1$
#1046000
b0 9
#1050000
0$
#1055000
1$
#1056000
b0 '
b0 ,
b1111 (
b1111 -
1&
#1060000
0$
#1065000
0"
10
0/
b0 !
b0 7
01
b0 4
1$
#1066000
b0 (
b0 -
0&
