TASK_2/RTL/gpio.v
module gpio_ip #(
    parameter [31:0] BASE_ADDR = 32'h2000_0000
)(
    input  wire        clk,
    input  wire        resetn,
    input  wire [31:0] addr,
    input  wire [31:0] wdata,
    input  wire [3:0]  wmask,
    input  wire        wstrb,
    input  wire        rstrb,
    output reg  [31:0] rdata,
    output reg  [31:0] gpio_out
);

    wire sel = (addr == BASE_ADDR);

    always @(posedge clk) begin
        if (!resetn) begin
            gpio_out <= 32'h00000000;
            rdata    <= 32'h00000000;
        end else begin
            if (sel && wstrb) begin
                if (wmask[0]) gpio_out[ 7: 0] <= wdata[ 7: 0];
                if (wmask[1]) gpio_out[15: 8] <= wdata[15: 8];
                if (wmask[2]) gpio_out[23:16] <= wdata[23:16];
                if (wmask[3]) gpio_out[31:24] <= wdata[31:24];
            end

            if (sel && rstrb) begin
                rdata <= gpio_out;
            end else if (!sel) begin
                rdata <= 32'h00000000;
            end
        end
    end
endmodule

TASK_2/RTL/gpio_tb.v
`timescale 1ns/1ps
`include "gpio.v"

module gpio_tb;
    reg        clk = 0;
    reg        resetn = 0;
    reg [31:0] addr = 32'h00000000;
    reg [31:0] wdata = 32'h00000000;
    reg [3:0]  wmask = 4'h0;
    reg        wstrb = 0;
    reg        rstrb = 0;
    wire [31:0] rdata;
    wire [31:0] gpio_out;

    gpio_ip #(.BASE_ADDR(32'h2000_0000)) dut (
        .clk(clk),
        .resetn(resetn),
        .addr(addr),
        .wdata(wdata),
        .wmask(wmask),
        .wstrb(wstrb),
        .rstrb(rstrb),
        .rdata(rdata),
        .gpio_out(gpio_out)
    );

    always #5 clk = ~clk;

    initial begin
        $dumpfile("gpio_tb.vcd");
        $dumpvars(0, gpio_tb);
    end

    initial begin
        #2 resetn = 0;
        #12 resetn = 1;

        // Full-word write and readback
        addr = 32'h2000_0000;
        wdata = 32'h11223344;
        wmask = 4'hf;
        wstrb = 1;
        rstrb = 0;
        #10;

        wstrb = 0;
        #10;

        rstrb = 1;
        #10;

        if (gpio_out !== 32'h11223344) begin
            $display("FAIL: gpio_out mismatch after full write: %h", gpio_out);
            $finish;
        end

        if (rdata !== 32'h11223344) begin
            $display("FAIL: rdata mismatch after full write: %h", rdata);
            $finish;
        end

        $display("PASS: full write/readback verified: %h", rdata);

        // Partial write using byte mask and readback
        wdata = 32'hA5A5A5A5;
        wmask = 4'b0011;
        wstrb = 1;
        rstrb = 0;
        #10;

        wstrb = 0;
        #10;

        rstrb = 1;
        #10;

        if (gpio_out !== 32'h1122A5A5) begin
            $display("FAIL: gpio_out mismatch after partial write: %h", gpio_out);
            $finish;
        end

        if (rdata !== 32'h1122A5A5) begin
            $display("FAIL: rdata mismatch after partial write: %h", rdata);
            $finish;
        end

        $display("PASS: partial write/readback verified: %h", rdata);
        $display("Waveform saved to gpio_tb.vcd");
        $finish;
    end
endmodule

TASK_2/RTL/gpio_tb.vcd
$date
	Wed Jul  1 12:14:29 2026
$end
$version
	Icarus Verilog
$end
$timescale
	1ps
$end
$scope module gpio_tb $end
$var wire 32 ! rdata [31:0] $end
$var wire 32 " gpio_out [31:0] $end
$var reg 32 # addr [31:0] $end
$var reg 1 $ clk $end
$var reg 1 % resetn $end
$var reg 1 & rstrb $end
$var reg 32 ' wdata [31:0] $end
$var reg 4 ( wmask [3:0] $end
$var reg 1 ) wstrb $end
$scope module dut $end
$var wire 32 * addr [31:0] $end
$var wire 1 $ clk $end
$var wire 1 % resetn $end
$var wire 1 & rstrb $end
$var wire 32 + wdata [31:0] $end
$var wire 4 , wmask [3:0] $end
$var wire 1 ) wstrb $end
$var wire 1 - sel $end
$var parameter 32 . BASE_ADDR $end
$var reg 32 / gpio_out [31:0] $end
$var reg 32 0 rdata [31:0] $end
$upscope $end
$upscope $end
$enddefinitions $end
$comment Show the parameter values. $end
$dumpall
b100000000000000000000000000000 .
$end
#0
$dumpvars
bx 0
bx /
0-
b0 ,
b0 +
b0 *
0)
b0 (
b0 '
0&
0%
0$
b0 #
bx "
bx !
$end
#5000
b0 !
b0 0
b0 "
b0 /
1$
#10000
0$
#14000
1)
b1111 (
b1111 ,
b10001001000100011001101000100 '
b10001001000100011001101000100 +
1-
b100000000000000000000000000000 #
b100000000000000000000000000000 *
1%
#15000
b10001001000100011001101000100 "
b10001001000100011001101000100 /
1$
#20000
0$
#24000
0)
#25000
1$
#30000
0$
#34000
1&
#35000
b10001001000100011001101000100 !
b10001001000100011001101000100 0
1$
#40000
0$
#44000
0&
1)
b11 (
b11 ,
b10100101101001011010010110100101 '
b10100101101001011010010110100101 +
#45000
b10001001000101010010110100101 "
b10001001000101010010110100101 /
1$
#50000
0$
#54000
0)
#55000
1$
#60000
0$
#64000
1&
#65000
b10001001000101010010110100101 !
b10001001000101010010110100101 0
1$
